setup.py
telemundo/__init__.py
telemundo/subtitles.py
telemundo.egg-info/PKG-INFO
telemundo.egg-info/SOURCES.txt
telemundo.egg-info/dependency_links.txt
telemundo.egg-info/top_level.txt
telemundo/utils/__init__.py
telemundo/utils/version.py