Metadata-Version: 1.1
Name: telemundo
Version: 0.1.3
Summary: Telemundo Py
Home-page: https://github.com/telemundo/telemundo-py
Author: Rodolfo Puig
Author-email: rodolfo.puig@nbcuni.com
License: MIT
Keywords: Telemundo
Platform: any
Classifier: Development Status :: 3 - Alpha
Classifier: Intended Audience :: Developers
Classifier: License :: OSI Approved :: MIT License
Classifier: Programming Language :: Python
Classifier: Topic :: Software Development :: Libraries :: Python Modules
